README.md
setup.cfg
setup.py
starlette_authentication/__init__.py
starlette_authentication/decorators.py
starlette_authentication.egg-info/PKG-INFO
starlette_authentication.egg-info/SOURCES.txt
starlette_authentication.egg-info/dependency_links.txt
starlette_authentication.egg-info/requires.txt
starlette_authentication.egg-info/top_level.txt