Metadata-Version: 1.0
Name: starlette-authentication
Version: 0.1
Summary: authentication for starlette
Home-page: https://github.com/zpdev/starlette-authentication
Author: zpzhou
Author-email: himoker@163.com
License: UNKNOWN
Platform: UNKNOWN
